mcap_ros1/__init__.py
mcap_ros1/decoder.py
mcap_ros1/py.typed
mcap_ros1/reader.py
mcap_ros1/writer.py
mcap_ros1/_vendor/__init__.py
mcap_ros1/_vendor/genmsg/__init__.py
mcap_ros1/_vendor/genmsg/base.py
mcap_ros1/_vendor/genmsg/command_line.py
mcap_ros1/_vendor/genmsg/deps.py
mcap_ros1/_vendor/genmsg/gentools.py
mcap_ros1/_vendor/genmsg/msg_loader.py
mcap_ros1/_vendor/genmsg/msgs.py
mcap_ros1/_vendor/genmsg/names.py
mcap_ros1/_vendor/genmsg/srvs.py
mcap_ros1/_vendor/genmsg/template_tools.py
mcap_ros1/_vendor/genpy/__init__.py
mcap_ros1/_vendor/genpy/base.py
mcap_ros1/_vendor/genpy/dynamic.py
mcap_ros1/_vendor/genpy/generate_initpy.py
mcap_ros1/_vendor/genpy/generate_numpy.py
mcap_ros1/_vendor/genpy/generate_struct.py
mcap_ros1/_vendor/genpy/generator.py
mcap_ros1/_vendor/genpy/genpy_main.py
mcap_ros1/_vendor/genpy/message.py
mcap_ros1/_vendor/genpy/rostime.py
mcap_ros1_support-0.7.4.dist-info/METADATA
mcap_ros1_support-0.7.4.dist-info/WHEEL
mcap_ros1_support-0.7.4.dist-info/top_level.txt
mcap_ros1_support-0.7.4.dist-info/RECORD
