Metadata-Version: 2.1
Name: mcap-ros1-support
Version: 0.7.4
Summary: ROS1 support for the Python MCAP library
Home-page: https://github.com/foxglove/mcap
Classifier: Programming Language :: Python :: 3
Classifier: License :: OSI Approved :: MIT License
Classifier: Operating System :: OS Independent
Requires-Python: >=3.7
Requires-Dist: mcap>=0.0.14
Requires-Dist: pyyaml
